spc4everybody/__init__.py
spc4everybody/hello_world.py
spc4everybody-0.0.1.dist-info/LICENSE.txt
spc4everybody-0.0.1.dist-info/METADATA
spc4everybody-0.0.1.dist-info/WHEEL
spc4everybody-0.0.1.dist-info/top_level.txt
spc4everybody-0.0.1.dist-info/RECORD
