Metadata-Version: 2.1
Name: spc4everybody
Version: 0.0.1
Summary: A powerful Python framework to perform Statistical Process Control (SPC) analysis
Author-email: Mikel Valencia <mikelv.dev@gmail.com>
Maintainer-email: Mikel Valencia <mikelv.dev@gmail.com>
License: Copyright (c) 2018 The Python Packaging Authority
Project-URL: Homepage, https://github.com/Mikel-Valencia/spc4everybody
Project-URL: Repository, https://github.com/Mikel-Valencia/spc4everybody.git
Project-URL: Issues, https://github.com/Mikel-Valencia/spc4everybody/issues
Keywords: statistics,manufacturing,spc,quality,control,engineering
Classifier: License :: OSI Approved :: MIT License
Classifier: Programming Language :: Python :: 3
Classifier: Development Status :: 1 - Planning
Classifier: Intended Audience :: Manufacturing
Classifier: Topic :: Scientific/Engineering
Requires-Python: >=3.10
License-File: LICENSE.txt
Requires-Dist: numpy
Provides-Extra: testing
Requires-Dist: pytest >=7.4 ; extra == 'testing'
Requires-Dist: mypy >=1.7 ; extra == 'testing'
Requires-Dist: flake8 >=6.1 ; extra == 'testing'
Requires-Dist: tox >=4.11 ; extra == 'testing'
